datati/.gitignore
datati/LICENSE
datati/README.md
datati/__init__.py
datati/dataset.py
datati/pipeline.py
datati/requirements.txt
datati/.idea/.gitignore
datati/.idea/datati.iml
datati/.idea/misc.xml
datati/.idea/modules.xml
datati/.idea/vcs.xml
datati/.idea/workspace.xml
datati/.idea/inspectionProfiles/Project_Default.xml
datati/.idea/inspectionProfiles/profiles_settings.xml
datati/.idea/scopes/datati.xml
datati/encoding/__init__.py
datati/encoding/quantization.py
datati/models/README.md
datati/models/__init__.py
datati/models/binary.py
datati/models/trees.py
datati/models/modelers/__init__.py
datati/models/modelers/filters.py
datati/models/modelers/numeric.py
datati/models/modelers/one_hot.py
datati-0.1.0.dist-info/METADATA
datati-0.1.0.dist-info/WHEEL
datati-0.1.0.dist-info/licenses/LICENSE
datati-0.1.0.dist-info/RECORD
