Metadata-Version: 2.1
Name: datati
Version: 0.1.0
Summary: Download and preprocess your dataset from any source, all in one place.
Project-URL: Homepage, https://github.com/msetzu/datati
Project-URL: Bug Tracker, https://github.com/msetzu/datati/issues
Author-email: Mattia Setzu <mattia.setzu@unipi.it>
License-File: LICENSE
Classifier: Development Status :: 4 - Beta
Classifier: Intended Audience :: Developers
Classifier: License :: OSI Approved :: GNU General Public License v3 or later (GPLv3+)
Classifier: Operating System :: OS Independent
Classifier: Programming Language :: Python :: 3.10
Requires-Python: >=3.10
Requires-Dist: aiohttp==3.8.4
Requires-Dist: aiosignal==1.3.1
Requires-Dist: async-timeout==4.0.2
Requires-Dist: attrs==23.1.0
Requires-Dist: bleach==6.0.0
Requires-Dist: build==0.10.0
Requires-Dist: certifi==2022.12.7
Requires-Dist: cffi==1.15.1
Requires-Dist: charset-normalizer==3.1.0
Requires-Dist: cryptography
Requires-Dist: datasets==2.11.0
Requires-Dist: dill==0.3.6
Requires-Dist: docutils==0.19
Requires-Dist: filelock==3.11.0
Requires-Dist: frozenlist==1.3.3
Requires-Dist: fsspec==2023.4.0
Requires-Dist: huggingface-hub==0.13.4
Requires-Dist: idna==3.4
Requires-Dist: importlib-metadata==6.4.1
Requires-Dist: jaraco-classes==3.2.3
Requires-Dist: jeepney==0.8.0
Requires-Dist: keyring==23.13.1
Requires-Dist: markdown-it-py==2.2.0
Requires-Dist: mdurl==0.1.2
Requires-Dist: more-itertools==9.1.0
Requires-Dist: multidict==6.0.4
Requires-Dist: multiprocess==0.70.14
Requires-Dist: numpy==1.24.2
Requires-Dist: packaging==23.1
Requires-Dist: pandas==2.0.0
Requires-Dist: pkginfo==1.9.6
Requires-Dist: pyarrow==11.0.0
Requires-Dist: pycparser==2.21
Requires-Dist: pygments==2.15.0
Requires-Dist: pyproject-hooks==1.0.0
Requires-Dist: python-dateutil==2.8.2
Requires-Dist: pytz==2023.3
Requires-Dist: pyyaml==6.0
Requires-Dist: readme-renderer==37.3
Requires-Dist: requests-toolbelt==0.10.1
Requires-Dist: requests==2.28.2
Requires-Dist: responses==0.18.0
Requires-Dist: rfc3986==2.0.0
Requires-Dist: rich==13.3.4
Requires-Dist: secretstorage==3.3.3
Requires-Dist: six==1.16.0
Requires-Dist: tomli==2.0.1
Requires-Dist: twine==4.0.2
Requires-Dist: typing-extensions==4.5.0
Requires-Dist: tzdata==2023.3
Requires-Dist: urllib3==1.26.15
Requires-Dist: webencodings==0.5.1
Requires-Dist: xxhash==3.2.0
Requires-Dist: yarl==1.8.2
Requires-Dist: zipp==3.15.0
